odoo10_addon_shopinvader_payment-10.0.2.0.0-nspkg.pth
odoo/addons/shopinvader_payment/README.rst
odoo/addons/shopinvader_payment/__init__.py
odoo/addons/shopinvader_payment/__manifest__.py
odoo/addons/shopinvader_payment/components/__init__.py
odoo/addons/shopinvader_payment/components/payment_transaction_event_listerner.py
odoo/addons/shopinvader_payment/models/__init__.py
odoo/addons/shopinvader_payment/models/payment_transaction.py
odoo/addons/shopinvader_payment/models/sale_order.py
odoo/addons/shopinvader_payment/models/shopinvader_backend.py
odoo/addons/shopinvader_payment/models/shopinvader_payment.py
odoo/addons/shopinvader_payment/readme/CONTRIBUTORS.rst
odoo/addons/shopinvader_payment/readme/DESCRIPTION.rst
odoo/addons/shopinvader_payment/security/ir.model.access.csv
odoo/addons/shopinvader_payment/services/__init__.py
odoo/addons/shopinvader_payment/services/abstract_payable_sale.py
odoo/addons/shopinvader_payment/services/cart.py
odoo/addons/shopinvader_payment/services/invader_payment_service.py
odoo/addons/shopinvader_payment/static/description/index.html
odoo/addons/shopinvader_payment/tests/__init__.py
odoo/addons/shopinvader_payment/tests/test_payment.py
odoo/addons/shopinvader_payment/views/backend_view.xml
odoo/addons/shopinvader_payment/views/shopinvader_menu.xml
odoo/addons/shopinvader_payment/views/shopinvader_payment_view.xml
odoo10_addon_shopinvader_payment-10.0.2.0.0.dist-info/METADATA
odoo10_addon_shopinvader_payment-10.0.2.0.0.dist-info/WHEEL
odoo10_addon_shopinvader_payment-10.0.2.0.0.dist-info/namespace_packages.txt
odoo10_addon_shopinvader_payment-10.0.2.0.0.dist-info/top_level.txt
odoo10_addon_shopinvader_payment-10.0.2.0.0.dist-info/RECORD
