Metadata-Version: 2.1
Name: odoo10-addon-shopinvader-payment
Version: 10.0.2.0.0
Summary: Payment integration for Shopinvader
Home-page: https://akretion.com
Author: Akretion
License: AGPL-3
Platform: UNKNOWN
Classifier: Programming Language :: Python
Classifier: Framework :: Odoo
Classifier: License :: OSI Approved :: GNU Affero General Public License v3
Requires-Python: ~=2.7
Requires-Dist: cerberus
Requires-Dist: odoo10-addon-account-payment-mode
Requires-Dist: odoo10-addon-account-payment-sale
Requires-Dist: odoo10-addon-component-event
Requires-Dist: odoo10-addon-invader-payment
Requires-Dist: odoo10-addon-invader-sale-payment
Requires-Dist: odoo10-addon-onchange-helper
Requires-Dist: odoo10-addon-sale-automatic-workflow-payment-mode
Requires-Dist: odoo10-addon-shopinvader
Requires-Dist: odoo (<10.1dev,>=10.0)
Requires-Dist: unidecode
